docstripy/__init__.py
docstripy/_version.py
docstripy/difference.py
docstripy/file_parser.py
docstripy/line_break.py
docstripy/lines_routines.py
docstripy/main.py
docstripy/write.py
docstripy/build_doc/__init__.py
docstripy/build_doc/main_builder.py
docstripy/build_doc/preprocessing.py
docstripy/google/__init__.py
docstripy/google/build_doc.py
docstripy/google/parse_doc.py
docstripy/numpy/__init__.py
docstripy/numpy/build_doc.py
docstripy/numpy/parse_doc.py
docstripy/parse_doc/__init__.py
docstripy/parse_doc/main_parser.py
docstripy/parse_doc/parse_params.py
docstripy/parse_doc/parse_signature.py
docstripy/parse_doc/postprocessing.py
docstripy/parse_doc/section_ranges.py
docstripy/parse_doc/signature.py
docstripy/rest/__init__.py
docstripy/rest/build_doc.py
docstripy/rest/parse_doc.py
docstripy-0.7.2.dist-info/LICENSE
docstripy-0.7.2.dist-info/METADATA
docstripy-0.7.2.dist-info/WHEEL
docstripy-0.7.2.dist-info/entry_points.txt
docstripy-0.7.2.dist-info/top_level.txt
docstripy-0.7.2.dist-info/RECORD
