Metadata-Version: 2.1
Name: docstripy
Version: 0.7.2
Summary: Merge your config files and set parameters from the command line in a simple way.
Author-email: Valentin Goldite <valentin.goldite@gmail.com>
Project-URL: Source, https://github.com/valentingol/docstripy
Keywords: numpy,docstring,numpydoc,python,format
Classifier: Programming Language :: Python :: 3
Requires-Python: >=3.7
License-File: LICENSE
Requires-Dist: nbformat
